nexonco/api.py
nexonco/query.py
nexonco/server.py
nexonco_mcp-0.1.17.dist-info/licenses/LICENSE
nexonco_mcp-0.1.17.dist-info/METADATA
nexonco_mcp-0.1.17.dist-info/WHEEL
nexonco_mcp-0.1.17.dist-info/entry_points.txt
nexonco_mcp-0.1.17.dist-info/top_level.txt
nexonco_mcp-0.1.17.dist-info/RECORD
