Metadata-Version: 2.4
Name: nexonco-mcp
Version: 0.1.17
Summary: An advanced MCP Server for accessing and analyzing clinical evidence data, with flexible search options to support precision medicine and oncology research.
Requires-Python: >=3.11
License-File: LICENSE
Requires-Dist: mcp[cli]==1.6.0
Requires-Dist: pandas>=2.2.3
Requires-Dist: requests>=2.32.3
Requires-Dist: starlette>=0.46.1
Requires-Dist: uvicorn>=0.34.0
Dynamic: license-file
